cvtoolbox/__init__.py
cvtoolbox/caffe.py
cvtoolbox-0.0.1.dist-info/LICENSE
cvtoolbox-0.0.1.dist-info/METADATA
cvtoolbox-0.0.1.dist-info/WHEEL
cvtoolbox-0.0.1.dist-info/top_level.txt
cvtoolbox-0.0.1.dist-info/RECORD
