Metadata-Version: 2.1
Name: cvtoolbox
Version: 0.0.1
Summary: A toolbox that integrates multiple tools
Home-page: https://github.com/xds95/cvtoolbox
Author: Xudong Shen
Author-email: sxd95@foxmail.com
License: UNKNOWN
Platform: UNKNOWN
Classifier: Programming Language :: Python :: 3
Classifier: License :: OSI Approved :: MIT License
Classifier: Operating System :: OS Independent
License-File: LICENSE
